MMSA/__init__.py
MMSA/__main__.py
MMSA/config.py
MMSA/data_loader.py
MMSA/run.py
MMSA/config/citations.json
MMSA/config/config_regression.json
MMSA/config/config_tune.json
MMSA/models/AMIO.py
MMSA/models/__init__.py
MMSA/models/missingTask/__init__.py
MMSA/models/missingTask/TFR_NET/__init__.py
MMSA/models/missingTask/TFR_NET/alignment.py
MMSA/models/missingTask/TFR_NET/fusion.py
MMSA/models/missingTask/TFR_NET/generator.py
MMSA/models/missingTask/TFR_NET/model.py
MMSA/models/multiTask/MLF_DNN.py
MMSA/models/multiTask/MLMF.py
MMSA/models/multiTask/MTFN.py
MMSA/models/multiTask/SELF_MM.py
MMSA/models/multiTask/__init__.py
MMSA/models/singleTask/BERT_MAG.py
MMSA/models/singleTask/EF_LSTM.py
MMSA/models/singleTask/Graph_MFN.py
MMSA/models/singleTask/LF_DNN.py
MMSA/models/singleTask/LMF.py
MMSA/models/singleTask/MCTN.py
MMSA/models/singleTask/MFM.py
MMSA/models/singleTask/MFN.py
MMSA/models/singleTask/MISA.py
MMSA/models/singleTask/MMIM.py
MMSA/models/singleTask/MULT.py
MMSA/models/singleTask/TFN.py
MMSA/models/singleTask/__init__.py
MMSA/models/subNets/AlignNets.py
MMSA/models/subNets/BertTextEncoder.py
MMSA/models/subNets/FeatureNets.py
MMSA/models/subNets/__init__.py
MMSA/models/subNets/transformers_encoder/__init__.py
MMSA/models/subNets/transformers_encoder/multihead_attention.py
MMSA/models/subNets/transformers_encoder/position_embedding.py
MMSA/models/subNets/transformers_encoder/transformer.py
MMSA/trains/ATIO.py
MMSA/trains/__init__.py
MMSA/trains/missingTask/TFR_NET.py
MMSA/trains/missingTask/__init__.py
MMSA/trains/multiTask/MLF_DNN.py
MMSA/trains/multiTask/MLMF.py
MMSA/trains/multiTask/MTFN.py
MMSA/trains/multiTask/SELF_MM.py
MMSA/trains/multiTask/__init__.py
MMSA/trains/singleTask/BERT_MAG.py
MMSA/trains/singleTask/EF_LSTM.py
MMSA/trains/singleTask/Graph_MFN.py
MMSA/trains/singleTask/LF_DNN.py
MMSA/trains/singleTask/LMF.py
MMSA/trains/singleTask/MCTN.py
MMSA/trains/singleTask/MFM.py
MMSA/trains/singleTask/MFN.py
MMSA/trains/singleTask/MISA.py
MMSA-2.2.1.dist-info/LICENSE
MMSA-2.2.1.dist-info/METADATA
MMSA-2.2.1.dist-info/WHEEL
MMSA-2.2.1.dist-info/top_level.txt
MMSA-2.2.1.dist-info/RECORD
