Metadata-Version: 2.1
Name: MMSA
Version: 2.2.1
Summary: Multimodal Sentiment Analysis Framework
Home-page: https://github.com/thuiar/MMSA
Author: THUIAR
Maintainer: FlameSky, Columbine21
Project-URL: Documentation, https://github.com/thuiar/MMSA/
Project-URL: Tracker, https://github.com/thuiar/MMSA/issues
Keywords: multimodal,sentiment analysis,mosi,mosei
Classifier: Programming Language :: Python :: 3.8
Classifier: Programming Language :: Python :: 3.9
Classifier: Programming Language :: Python :: 3.10
Classifier: Programming Language :: Python :: 3.11
Classifier: License :: OSI Approved :: MIT License
Classifier: Operating System :: OS Independent
Requires-Python: >=3.8
License-File: LICENSE
Requires-Dist: torch (>=1.9.1)
Requires-Dist: transformers (>=4.4.0)
Requires-Dist: numpy (>=1.20.3)
Requires-Dist: pandas (>=1.2.5)
Requires-Dist: tqdm (>=4.62.2)
Requires-Dist: nvidia-ml-py3 (>=7.352.0)
Requires-Dist: scikit-learn (>=0.24.2)
Requires-Dist: easydict (>=1.9)
